Metadata-Version: 2.1
Name: odc-pycommons
Version: 0.3.2
Summary: OculusD Python Commons Library
Home-page: https://www.oculusd.com/
Author: OculusD
Author-email: info@oculusd.com
License: UNKNOWN
Download-URL: https://github.com/oculusd/odc_pycommons/archive/release-0.3.2.tar.gz
Project-URL: Bug Reports, https://www.oculusd.com/
Project-URL: Funding, https://www.oculusd.com/
Project-URL: Say Thanks!, https://www.oculusd.com/
Project-URL: Source, https://www.oculusd.com/
Keywords: cli library iot oculusd
Platform: UNKNOWN
Classifier: Development Status :: 4 - Beta
Classifier: Intended Audience :: Developers
Classifier: Topic :: Internet
Classifier: Topic :: Software Development :: Libraries
Classifier: License :: OSI Approved :: GNU Lesser General Public License v3 or later (LGPLv3+)
Classifier: Programming Language :: Python :: 3.6
Classifier: Programming Language :: Python :: 3.7
Provides-Extra: dev
Provides-Extra: test
